{
  "1": {
    "isi": "Allah tidak akan mengubah nasib suatu kaum kecuali kaum itu sendiri yang mengubahnya.",
    "sumber": "Al-Qur'an (Ar-Ra'd: 11), Surah Ar-Ra'd ayat 11"
  },
  "2": {
    "isi": "Banyak bersedekah, walaupun hanya dengan setengah kurma.",
    "sumber": "Hadits Riwayat Bukhari dan Muslim"
  },
  "3": {
    "isi": "Janganlah kamu menyepelekan dosa kecil, sesungguhnya gunung itu terbentuk dari batu kerikil.",
    "sumber": "Hadits Riwayat Ahmad"
  },
  "4": {
    "isi": "Orang yang paling sempurna imannya adalah yang paling baik akhlaknya.",
    "sumber": "Hadits Riwayat At-Tirmidzi"
  },
  "5": {
    "isi": "Doa seorang Muslim untuk saudaranya yang tidak ia lihat adalah doa yang mustajab.",
    "sumber": "Hadits Riwayat Muslim"
  },
  "6": {
    "isi": "Allah menciptakan manusia dalam bentuk sebaik-baik rupa.",
    "sumber": "Al-Qur'an (At-Tin: 4), Surah At-Tin ayat 4"
  },
  "7": {
    "isi": "Sungguh, setiap amal perbuatan itu tergantung niatnya.",
    "sumber": "Hadits Riwayat Bukhari dan Muslim"
  },
  "8": {
    "isi": "Janganlah kamu merendahkan amal kecil, karena gunung itu terbentuk dari kerikil-kerikil kecil.",
    "sumber": "Hadits Riwayat Ahmad"
  },
  "9": {
    "isi": "Sesungguhnya setiap langkahmu yang menuju ke masjid, akan menghapuskan dosa-dosamu dan menaikkan derajatmu.",
    "sumber": "Hadits Riwayat Muslim"
  },
  "10": {
    "isi": "Mintalah pertolongan kepada Allah dan bersabarlah. Sesungguhnya, Allah bersama orang-orang yang sabar.",
    "sumber": "Al-Baqarah (2:153), Surah Al-Baqarah ayat 153"
  }
}
